idc_index_data/__init__.py
idc_index_data/_version.py
idc_index_data/_version.pyi
idc_index_data/analysis_results_index.parquet
idc_index_data/analysis_results_index.sql
idc_index_data/analysis_results_index_schema.json
idc_index_data/clinical_index.sql
idc_index_data/clinical_index_schema.json
idc_index_data/collections_index.parquet
idc_index_data/collections_index.sql
idc_index_data/collections_index_schema.json
idc_index_data/idc_index.parquet
idc_index_data/idc_index.sql
idc_index_data/idc_index_schema.json
idc_index_data/prior_versions_index.parquet
idc_index_data/prior_versions_index.sql
idc_index_data/prior_versions_index_schema.json
idc_index_data/py.typed
idc_index_data/seg_index.sql
idc_index_data/seg_index_schema.json
idc_index_data/sm_index.sql
idc_index_data/sm_index_schema.json
idc_index_data/sm_instance_index.sql
idc_index_data/sm_instance_index_schema.json
idc_index_data-23.3.1.dist-info/METADATA
idc_index_data-23.3.1.dist-info/WHEEL
idc_index_data-23.3.1.dist-info/licenses/LICENSE
idc_index_data-23.3.1.dist-info/RECORD
