Metadata-Version: 2.4
Name: idc-index-data
Version: 23.3.1
Summary: ImagingDataCommons index to query and download data.
Project-URL: Homepage, https://github.com/ImagingDataCommons/idc-index-data
Project-URL: Bug Tracker, https://github.com/ImagingDataCommons/idc-index-data/issues
Project-URL: Discussions, https://discourse.canceridc.dev/
Project-URL: Changelog, https://github.com/ImagingDataCommons/idc-index-data/releases
Author-email: Andrey Fedorov <andrey.fedorov@gmail.com>, Vamsi Thiriveedhi <vthiriveedhi@mgh.harvard.edu>, Jean-Christophe Fillion-Robin <jchris.fillionr@kitware.com>
License: Copyright 2024 Andrey Fedorov
License-File: LICENSE
Classifier: Development Status :: 4 - Beta
Classifier: Intended Audience :: Developers
Classifier: Intended Audience :: Science/Research
Classifier: License :: OSI Approved :: MIT License
Classifier: Operating System :: OS Independent
Classifier: Programming Language :: Python
Classifier: Programming Language :: Python :: 3
Classifier: Programming Language :: Python :: 3 :: Only
Classifier: Programming Language :: Python :: 3.10
Classifier: Programming Language :: Python :: 3.11
Classifier: Programming Language :: Python :: 3.12
Classifier: Topic :: Scientific/Engineering
Classifier: Typing :: Typed
Requires-Python: >=3.10
Requires-Dist: google-cloud-bigquery
Provides-Extra: dev
Requires-Dist: pytest-cov>=3; extra == 'dev'
Requires-Dist: pytest>=6; extra == 'dev'
Provides-Extra: docs
Requires-Dist: furo>=2023.08.17; extra == 'docs'
Requires-Dist: myst-parser>=0.13; extra == 'docs'
Requires-Dist: sphinx-autodoc-typehints; extra == 'docs'
Requires-Dist: sphinx-copybutton; extra == 'docs'
Requires-Dist: sphinx>=7.0; extra == 'docs'
Provides-Extra: test
Requires-Dist: pandas; extra == 'test'
Requires-Dist: pyarrow; extra == 'test'
Requires-Dist: pytest-cov>=3; extra == 'test'
Requires-Dist: pytest>=6; extra == 'test'
